pyddosX/__init__.py
pyddosX/pyddosX.py
py_ddosX-1.1.2.dist-info/METADATA
py_ddosX-1.1.2.dist-info/WHEEL
py_ddosX-1.1.2.dist-info/entry_points.txt
py_ddosX-1.1.2.dist-info/top_level.txt
py_ddosX-1.1.2.dist-info/RECORD
