Metadata-Version: 2.1
Name: py-ddosX
Version: 1.1.2
Summary: 🔗 Package Guide On https://github.com/mohamedlunar/py-ddos3
Home-page: https://github.com/mohamedlunar/py-ddos3
Author: MohamedLunar
Author-email: contact.mohamedlunardev@gmail.com
Classifier: Programming Language :: Python :: 3
Classifier: License :: OSI Approved :: MIT License
Classifier: Operating System :: OS Independent
Requires-Python: >=3.6
